{
  "contacts": [
    {
      "id": 1,
      "firstName": "John",
      "lastName": "Carmack",
      "street": "10 Keen Street",
      "city": "London"
    },
    {
      "firstName": "ttt",
      "lastName": "ttt",
      "street": "27 Ruscoe Road",
      "city": "London",
      "email": "czdavid93@gmail.com",
      "linkedin": "",
      "twitter": "",
      "id": 2
    },
    {
      "firstName": "Oliver",
      "lastName": "Bonas",
      "street": "Stebondale Street",
      "city": "London",
      "email": "czdavid93@gmail.com",
      "linkedin": "",
      "twitter": "",
      "id": 3
    }
  ]
}